setup.py
SySApp.egg-info/PKG-INFO
SySApp.egg-info/SOURCES.txt
SySApp.egg-info/dependency_links.txt
SySApp.egg-info/top_level.txt
sysapp/__init__.py
sysapp/adv_module.py
sysapp/dll.py