Metadata-Version: 2.1
Name: SySApp
Version: 0.0.5
Summary: SyS App official module in Python. (Work in progress...)
Author: Runkang Chen
Author-email: help.informatic365@gmail.com
